slerp/__init__.py
slerp/apigen.py
slerp/app.py
slerp/consul.py
slerp/decorator.py
slerp/encoder.py
slerp/entity.py
slerp/exception.py
slerp/logger.py
slerp/response.py
slerp/sender.py
slerp/string_utils.py
slerp/testgen.py
slerp/validator.py
slerp/visitor.py
templates/__init__.py
templates/api_add.txt
templates/api_all.txt
templates/api_base.txt
templates/api_delete.txt
templates/api_find.txt
templates/api_pagging.txt
templates/api_update.txt
templates/service_add.txt
templates/service_all.txt
templates/service_base.txt
templates/service_delete.txt
templates/service_find.txt
templates/service_pagging.txt
templates/service_update.txt
templates/test_api.txt
templates/test_base.txt
tests/__init__.py
tests/test_entity.py
tests/test_string.py
tests/test_validator.py
slerp_py-0.0.26.dist-info/METADATA
slerp_py-0.0.26.dist-info/WHEEL
slerp_py-0.0.26.dist-info/entry_points.txt
slerp_py-0.0.26.dist-info/top_level.txt
slerp_py-0.0.26.dist-info/RECORD
