Metadata-Version: 2.1
Name: slerp-py
Version: 0.0.26
Summary: Support library for slerp project
Home-page: https://github.com/kiditz/slerpio
Author: Rifky Aditya Bastara
Author-email: kiditzbastara@gmail.com
License: Apache
Platform: any
Classifier: Development Status :: 1 - Planning
Classifier: Environment :: Web Environment
Classifier: Intended Audience :: Developers
Classifier: License :: OSI Approved :: Apache Software License
Classifier: Operating System :: OS Independent
Classifier: Programming Language :: Python
Classifier: Programming Language :: Python :: 2
Classifier: Programming Language :: Python :: 2.7
Classifier: Programming Language :: Python :: 3
Classifier: Programming Language :: Python :: 3.4
Classifier: Programming Language :: Python :: 3.5
Classifier: Programming Language :: Python :: 3.6
Classifier: Topic :: Internet :: WWW/HTTP :: Dynamic Content
Classifier: Topic :: Software Development :: Libraries :: Python Modules
Requires-Dist: consulate
Requires-Dist: Flask
Requires-Dist: Flask-SQLAlchemy
Requires-Dist: Flask-Caching
Requires-Dist: dnspython3
Requires-Dist: kafka-python
Provides-Extra: test
Requires-Dist: mock ; extra == 'test'
Requires-Dist: six ; extra == 'test'
Requires-Dist: coverage ; extra == 'test'
Requires-Dist: pytest ; extra == 'test'
